privex/__init__.py
privex/rpcemulator/__init__.py
privex/rpcemulator/base.py
privex/rpcemulator/bitcoin.py
rpcemulator-0.8.1.dist-info/LICENSE
rpcemulator-0.8.1.dist-info/METADATA
rpcemulator-0.8.1.dist-info/WHEEL
rpcemulator-0.8.1.dist-info/top_level.txt
rpcemulator-0.8.1.dist-info/RECORD
