Metadata-Version: 2.1
Name: rpcemulator
Version: 0.8.1
Summary: A collection of JsonRPC API emulators, designed for unit testing
Home-page: https://github.com/Privex/rpcemulator
Author: Chris (Someguy123) @ Privex
Author-email: chris@privex.io
License: MIT
Platform: UNKNOWN
Classifier: Programming Language :: Python :: 3
Classifier: Programming Language :: Python :: 3.6
Classifier: Programming Language :: Python :: 3.7
Classifier: Programming Language :: Python :: 3.8
Classifier: License :: OSI Approved :: MIT License
Classifier: Operating System :: OS Independent
Requires-Dist: privex-helpers (>=2.0.0)
Requires-Dist: privex-jsonrpc (>=1.1.2)
Requires-Dist: Faker (>=2.0.0)
Requires-Dist: jsonrpcserver (>=4.0.0)
